setup.py
dis_tri_but_ion.egg-info/PKG-INFO
dis_tri_but_ion.egg-info/SOURCES.txt
dis_tri_but_ion.egg-info/dependency_links.txt
dis_tri_but_ion.egg-info/not-zip-safe
dis_tri_but_ion.egg-info/top_level.txt
distributions/Binomialdistribution.py
distributions/Gaussiandistribution.py
distributions/Generaldistribution.py
distributions/__init__.py